cubicweb_email/__init__.py
cubicweb_email/__pkginfo__.py
cubicweb_email/emailcites.py
cubicweb_email/entities.py
cubicweb_email/hooks.py
cubicweb_email/schema.py
cubicweb_email/testutils.py
cubicweb_email/i18n/en.po
cubicweb_email/i18n/fr.po
cubicweb_email/migration/1.1.0_Any.py
cubicweb_email/migration/1.1.1_Any.py
cubicweb_email/migration/1.11.0_Any.py
cubicweb_email/migration/1.2.2_Any.py
cubicweb_email/migration/1.4.1_Any.py
cubicweb_email/migration/postcreate.py
cubicweb_email/views/__init__.py
cubicweb_email/views/email.py
cubicweb_email-2.1.0.data/scripts/cw-mboximport
cwemail/__init__.py
cwemail/mboximport.py
cubicweb_email-2.1.0.dist-info/METADATA
cubicweb_email-2.1.0.dist-info/WHEEL
cubicweb_email-2.1.0.dist-info/entry_points.txt
cubicweb_email-2.1.0.dist-info/top_level.txt
cubicweb_email-2.1.0.dist-info/RECORD
