Metadata-Version: 2.4
Name: cubicweb-email
Version: 2.1.0
Summary: email component for the CubicWeb framework
Home-page: http://www.cubicweb.org/project/cubicweb-email
Author: Logilab
Author-email: contact@logilab.fr
License: LGPL
Classifier: Environment :: Web Environment
Classifier: Framework :: CubicWeb
Classifier: Programming Language :: Python
Classifier: Programming Language :: JavaScript
Requires-Dist: cubicweb<6.0.0,>=4.0.0
Requires-Dist: cubicweb_web<2.0.0,>=1.6.0
Requires-Dist: cubicweb-file<5.0.0,>=4.2.0
Requires-Dist: cwclientlib<2.0.0,>=1.6.0
Dynamic: author
Dynamic: author-email
Dynamic: classifier
Dynamic: description
Dynamic: home-page
Dynamic: license
Dynamic: requires-dist
Dynamic: summary
